Metadata-Version: 2.1
Name: funcodec
Version: 0.2.0
Summary: FunCodec: A Fundamental, Reproducible and Integrable Open-source Toolkit for Neural Speech Codec
Home-page: https://github.com/alibaba-damo-academy/FunCodec.git
Author: Speech Lab, Alibaba Group, China
Author-email: funcodec@list.alibaba-inc.com
License: The MIT License
Classifier: Programming Language :: Python
Classifier: Programming Language :: Python :: 3
Classifier: Programming Language :: Python :: 3.7
Classifier: Programming Language :: Python :: 3.8
Classifier: Programming Language :: Python :: 3.9
Classifier: Development Status :: 5 - Production/Stable
Classifier: Intended Audience :: Science/Research
Classifier: Operating System :: POSIX :: Linux
Classifier: License :: OSI Approved :: Apache Software License
Classifier: Topic :: Software Development :: Libraries :: Python Modules
Requires-Python: >=3.8.0
License-File: LICENSE
Requires-Dist: setuptools >=38.5.1
Requires-Dist: typeguard ==2.13.3
Requires-Dist: humanfriendly
Requires-Dist: scipy >=1.4.1
Requires-Dist: librosa >=0.8.0
Requires-Dist: jamo ==0.4.1
Requires-Dist: PyYAML >=5.1.2
Requires-Dist: soundfile >=0.10.2
Requires-Dist: h5py >=2.10.0
Requires-Dist: kaldiio >=2.17.0
Requires-Dist: torch-complex
Requires-Dist: nltk >=3.4.5
Requires-Dist: sentencepiece
Requires-Dist: pypinyin <=0.44.0
Requires-Dist: espnet-tts-frontend
Requires-Dist: pytorch-wpe
Requires-Dist: editdistance ==0.5.2
Requires-Dist: tensorboard >=1.15
Requires-Dist: g2p
Requires-Dist: oss2
Requires-Dist: local-attention
Requires-Dist: einops >=0.6.0
Requires-Dist: thop >=0.1.1.post2209072238
Requires-Dist: alias-free-torch >=0.0.6
Requires-Dist: phaseaug >=1.0.1
Provides-Extra: all
Requires-Dist: torch-optimizer ; extra == 'all'
Requires-Dist: fairscale ; extra == 'all'
Requires-Dist: transformers ; extra == 'all'
Requires-Dist: torch >=1.12 ; extra == 'all'
Requires-Dist: torch-complex >=0.4.3 ; extra == 'all'
Requires-Dist: torchaudio >=0.12.0 ; extra == 'all'
Requires-Dist: torchvision >=0.13.0 ; extra == 'all'
Requires-Dist: numpy >=1.23.5 ; extra == 'all'
Requires-Dist: numba >=0.56.4 ; extra == 'all'
Requires-Dist: editdistance >=0.5.2 ; extra == 'all'
Requires-Dist: wandb ; extra == 'all'
Requires-Dist: espnet-model-zoo ; extra == 'all'
Provides-Extra: doc
Requires-Dist: Jinja2 <3.1 ; extra == 'doc'
Requires-Dist: Sphinx ==2.1.2 ; extra == 'doc'
Requires-Dist: sphinx-rtd-theme >=0.2.4 ; extra == 'doc'
Requires-Dist: sphinx-argparse >=0.2.5 ; extra == 'doc'
Requires-Dist: commonmark ==0.8.1 ; extra == 'doc'
Requires-Dist: recommonmark >=0.4.0 ; extra == 'doc'
Requires-Dist: nbsphinx >=0.4.2 ; extra == 'doc'
Requires-Dist: sphinx-markdown-tables >=0.0.12 ; extra == 'doc'
Provides-Extra: recipe
Requires-Dist: espnet-model-zoo ; extra == 'recipe'
Provides-Extra: test
Requires-Dist: pytest >=3.3.0 ; extra == 'test'
Requires-Dist: pytest-timeouts >=1.2.1 ; extra == 'test'
Requires-Dist: pytest-pythonpath >=0.7.3 ; extra == 'test'
Requires-Dist: pytest-cov >=2.7.1 ; extra == 'test'
Requires-Dist: hacking >=2.0.0 ; extra == 'test'
Requires-Dist: mock >=2.0.0 ; extra == 'test'
Requires-Dist: pycodestyle ; extra == 'test'
Requires-Dist: jsondiff <2.0.0,>=1.2.0 ; extra == 'test'
Requires-Dist: flake8 >=3.7.8 ; extra == 'test'
Requires-Dist: flake8-docstrings >=1.3.1 ; extra == 'test'
Requires-Dist: black ; extra == 'test'
Requires-Dist: editdistance >=0.5.2 ; extra == 'test'
Requires-Dist: wandb ; extra == 'test'
Provides-Extra: train
Requires-Dist: editdistance >=0.5.2 ; extra == 'train'
Requires-Dist: wandb ; extra == 'train'
